cadbiom_cmd/__init__.py
cadbiom_cmd/cadbiom_cmd.py
cadbiom_cmd/interaction_graph.py
cadbiom_cmd/models.py
cadbiom_cmd/solution_merge.py
cadbiom_cmd/solution_search.py
cadbiom_cmd/solution_sort.py
cadbiom_cmd/tools/__init__.py
cadbiom_cmd/tools/graphs.py
cadbiom_cmd/tools/models.py
cadbiom_cmd/tools/solutions.py
cadbiom_cmd-1.1.0.dist-info/METADATA
cadbiom_cmd-1.1.0.dist-info/RECORD
cadbiom_cmd-1.1.0.dist-info/WHEEL
cadbiom_cmd-1.1.0.dist-info/entry_points.txt
cadbiom_cmd-1.1.0.dist-info/top_level.txt
test/__init__.py
test/test_mac.py
test/test_python_api.py
test/test_trajectories_parsing.py
