Metadata-Version: 2.1
Name: cadbiom-cmd
Version: 1.1.0
Summary: Command line tools using the Cadbiom library
Home-page: https://gitlab.inria.fr/pvignet/cadbiom
Author: pvignet
Author-email: pierre.vignet@irisa.fr
License: UNKNOWN
Platform: UNKNOWN
Classifier: Environment :: Console
Classifier: Development Status :: 4 - Beta
Classifier: License :: OSI Approved :: GNU General Public License v3 or later (GPLv3+)
Classifier: Natural Language :: French
Classifier: Intended Audience :: Developers
Classifier: Operating System :: OS Independent
Classifier: Programming Language :: Python :: 2.7
Classifier: Topic :: Scientific/Engineering :: Bio-Informatics
Provides-Extra: dev
Provides-Extra: matplotlib
Requires-Dist: futures
Requires-Dist: cadbiom
Requires-Dist: futures
Provides-Extra: dev
Requires-Dist: sphinx (<2); extra == 'dev'
Requires-Dist: sphinx-argparse; extra == 'dev'
Provides-Extra: matplotlib
Requires-Dist: matplotlib (<2); extra == 'matplotlib'
